opengeodeweb_microservice/__init__.py
opengeodeweb_microservice/py.typed
opengeodeweb_microservice/schemas.py
opengeodeweb_microservice/database/__init__.py
opengeodeweb_microservice/database/base.py
opengeodeweb_microservice/database/connection.py
opengeodeweb_microservice/database/data.py
opengeodeweb_microservice-1.0.12.dist-info/licenses/LICENSE
opengeodeweb_microservice-1.0.12.dist-info/METADATA
opengeodeweb_microservice-1.0.12.dist-info/WHEEL
opengeodeweb_microservice-1.0.12.dist-info/top_level.txt
opengeodeweb_microservice-1.0.12.dist-info/RECORD
