Metadata-Version: 2.4
Name: OpenGeodeWeb-Microservice
Version: 1.0.12
Summary: Database model and ORM layer for OpenGeodeWeb ecosystem
Author-email: Geode-solutions <team-web@geode-solutions.com>
Project-URL: Homepage, https://github.com/Geode-solutions/OpenGeodeWeb-Microservice
Project-URL: Bug Tracker, https://github.com/Geode-solutions/OpenGeodeWeb-Microservice/issues
Classifier: Programming Language :: Python :: 3
Classifier: License :: OSI Approved :: MIT License
Classifier: Operating System :: OS Independent
Requires-Python: <3.13,>=3.9
License-File: LICENSE
Requires-Dist: dataclasses-json>=0
Requires-Dist: fastjsonschema==2.21.1
Requires-Dist: greenlet>=3
Requires-Dist: marshmallow>=3
Requires-Dist: mypy-extensions>=1
Requires-Dist: packaging==25.0
Requires-Dist: sqlalchemy>=2
Requires-Dist: typing-extensions>=4
Requires-Dist: typing-inspect>=0
Dynamic: license-file
